{
  "n": 10,
  "selection_rule": "Sports-only, multi-episode, both proposed and final outcomes non-null. Curated to span Request-voiding and Repeated adapter-routed types.",
  "examples": [
    {
      "id": "33a11049",
      "question_text": "Big Bash League: Brisbane Heat vs Adelaide Strikers (Game 1) - Team Top Batter Brisbane Heat Winner",
      "category": "sports",
      "chain_type": "Request-voiding chain",
      "n_episodes": 2,
      "request_sequence": [
        {
          "request_idx": 1,
          "proposed": "No",
          "was_disputed": true,
          "final_outcome": "Other",
          "proposal_time": 1766835103,
          "dispute_time": 1766835741,
          "final_time": 1767056465
        },
        {
          "request_idx": 2,
          "proposed": "No",
          "was_disputed": false,
          "final_outcome": "No",
          "proposal_time": 1766836727,
          "dispute_time": null,
          "final_time": 1766844289
        }
      ]
    },
    {
      "id": "a62a77ab",
      "question_text": "Will Nico Hulkenberg win the 2025 F1 Brazilian Grand Prix?",
      "category": "sports",
      "chain_type": "Request-voiding chain",
      "n_episodes": 2,
      "request_sequence": [
        {
          "request_idx": 1,
          "proposed": "No",
          "was_disputed": true,
          "final_outcome": "Other",
          "proposal_time": 1762715595,
          "dispute_time": 1762715693,
          "final_time": 1762908089
        },
        {
          "request_idx": 2,
          "proposed": "No",
          "was_disputed": false,
          "final_outcome": "No",
          "proposal_time": 1762730739,
          "dispute_time": null,
          "final_time": 1762738183
        }
      ]
    },
    {
      "id": "cd400259",
      "question_text": "Will Leonard Gates win the PDC World Darts Championship?",
      "category": "sports",
      "chain_type": "Request-voiding chain",
      "n_episodes": 2,
      "request_sequence": [
        {
          "request_idx": 1,
          "proposed": "No",
          "was_disputed": true,
          "final_outcome": "Other",
          "proposal_time": 1766436209,
          "dispute_time": 1766436795,
          "final_time": 1766709969
        },
        {
          "request_idx": 2,
          "proposed": "No",
          "was_disputed": true,
          "final_outcome": "No",
          "proposal_time": 1766437225,
          "dispute_time": 1766437947,
          "final_time": 1766709977
        }
      ]
    },
    {
      "id": "0024be34",
      "question_text": "Will Rex Regum Qeon win the 2025 Valorant Esports World Cup Tournament?",
      "category": "sports",
      "chain_type": "Request-voiding chain",
      "n_episodes": 2,
      "request_sequence": [
        {
          "request_idx": 1,
          "proposed": "No",
          "was_disputed": true,
          "final_outcome": "Other",
          "proposal_time": 1752153260,
          "dispute_time": 1752153398,
          "final_time": 1752367560
        },
        {
          "request_idx": 2,
          "proposed": "No",
          "was_disputed": false,
          "final_outcome": "No",
          "proposal_time": 1752154118,
          "dispute_time": null,
          "final_time": 1752161342
        }
      ]
    },
    {
      "id": "e69895b5",
      "question_text": "Will Liam Lawson win the 2025 F1 Brazilian Grand Prix?",
      "category": "sports",
      "chain_type": "Request-voiding chain",
      "n_episodes": 2,
      "request_sequence": [
        {
          "request_idx": 1,
          "proposed": "No",
          "was_disputed": true,
          "final_outcome": "Other",
          "proposal_time": 1762715595,
          "dispute_time": 1762715755,
          "final_time": 1763080856
        },
        {
          "request_idx": 2,
          "proposed": "No",
          "was_disputed": false,
          "final_outcome": "No",
          "proposal_time": 1762730741,
          "dispute_time": null,
          "final_time": 1762738125
        }
      ]
    },
    {
      "id": "360df1a6",
      "question_text": "Will F1 be the #1 searched movie on Google this year?",
      "category": "sports",
      "chain_type": "Repeated adapter-routed request",
      "n_episodes": 2,
      "request_sequence": [
        {
          "request_idx": 1,
          "proposed": "No",
          "was_disputed": true,
          "final_outcome": "No",
          "proposal_time": 1764822205,
          "dispute_time": 1764828231,
          "final_time": 1765154783
        },
        {
          "request_idx": 2,
          "proposed": "No",
          "was_disputed": false,
          "final_outcome": "No",
          "proposal_time": 1764828317,
          "dispute_time": null,
          "final_time": 1764835589
        }
      ]
    },
    {
      "id": "897716e8",
      "question_text": "Will Sungjae Im win the 2025 Wyndham Championship?",
      "category": "sports",
      "chain_type": "Repeated adapter-routed request",
      "n_episodes": 2,
      "request_sequence": [
        {
          "request_idx": 1,
          "proposed": "No",
          "was_disputed": true,
          "final_outcome": "No",
          "proposal_time": 1754254463,
          "dispute_time": 1754254691,
          "final_time": 1754612759
        },
        {
          "request_idx": 2,
          "proposed": "No",
          "was_disputed": false,
          "final_outcome": "No",
          "proposal_time": 1754255201,
          "dispute_time": null,
          "final_time": 1754262553
        }
      ]
    },
    {
      "id": "5af77ce8",
      "question_text": "Big Bash League: Sydney Sixers vs Hobart Hurricanes (Game 1) - Most Sixes Draw",
      "category": "sports",
      "chain_type": "Repeated adapter-routed request",
      "n_episodes": 2,
      "request_sequence": [
        {
          "request_idx": 1,
          "proposed": "Yes",
          "was_disputed": true,
          "final_outcome": "No",
          "proposal_time": 1768109472,
          "dispute_time": 1768111238,
          "final_time": 1768438126
        },
        {
          "request_idx": 2,
          "proposed": "No",
          "was_disputed": false,
          "final_outcome": "No",
          "proposal_time": 1768111812,
          "dispute_time": null,
          "final_time": 1768119786
        }
      ]
    },
    {
      "id": "7ba1fba3",
      "question_text": "Will the New England Patriots finish with the best record in the NFL?",
      "category": "sports",
      "chain_type": "Repeated adapter-routed request",
      "n_episodes": 2,
      "request_sequence": [
        {
          "request_idx": 1,
          "proposed": "Yes",
          "was_disputed": true,
          "final_outcome": "Yes",
          "proposal_time": 1767585205,
          "dispute_time": 1767588539,
          "final_time": 1767919568
        },
        {
          "request_idx": 2,
          "proposed": "Yes",
          "was_disputed": false,
          "final_outcome": "Yes",
          "proposal_time": 1767590973,
          "dispute_time": null,
          "final_time": 1767604757
        }
      ]
    },
    {
      "id": "46e20d19",
      "question_text": "Will David Puig have the best finish at the 2025 Open Championship?",
      "category": "sports",
      "chain_type": "Repeated adapter-routed request",
      "n_episodes": 2,
      "request_sequence": [
        {
          "request_idx": 1,
          "proposed": "No",
          "was_disputed": true,
          "final_outcome": "No",
          "proposal_time": 1752793522,
          "dispute_time": 1752794694,
          "final_time": 1753057867
        },
        {
          "request_idx": 2,
          "proposed": "No",
          "was_disputed": false,
          "final_outcome": "No",
          "proposal_time": 1752795108,
          "dispute_time": null,
          "final_time": 1752802330
        }
      ]
    }
  ]
}